fastapi_controller/__init__.py
fastapi_controller/cbv.py
fastapi_controller/controller.py
fastapi_controller/controller_utils.py
fastapi_controller-0.0.8.dist-info/LICENSE
fastapi_controller-0.0.8.dist-info/METADATA
fastapi_controller-0.0.8.dist-info/WHEEL
fastapi_controller-0.0.8.dist-info/top_level.txt
fastapi_controller-0.0.8.dist-info/RECORD
