Metadata-Version: 2.1
Name: fastapi-controller
Version: 0.0.8
Summary: Package to create API controllers that can inherit routes
Home-page: https://github.com/aksharpatel47/fastapi-controller
Author: Akshar Patel
Author-email: akshar.patel.47@gmail.com
License: UNKNOWN
Platform: UNKNOWN
Requires-Python: >=3.6
License-File: LICENSE
Requires-Dist: fastapi-utils (>=0.2.1)
Requires-Dist: fastapi[all] (>=0.65.0)
Requires-Dist: typing-inspect (>=0.7.1)
